asphalt/py4j/__init__.py
asphalt/py4j/component.py
asphalt_py4j-4.0.0.dist-info/LICENSE
asphalt_py4j-4.0.0.dist-info/METADATA
asphalt_py4j-4.0.0.dist-info/WHEEL
asphalt_py4j-4.0.0.dist-info/entry_points.txt
asphalt_py4j-4.0.0.dist-info/top_level.txt
asphalt_py4j-4.0.0.dist-info/RECORD
