Metadata-Version: 2.1
Name: asphalt-py4j
Version: 4.0.0
Summary: Py4J integration component for the Asphalt framework
Author-email: Alex Grönholm <alex.gronholm@nextday.fi>
License: Apache License 2.0
Project-URL: Homepage, https://github.com/asphalt-framework/asphalt-py4j
Classifier: Development Status :: 5 - Production/Stable
Classifier: Intended Audience :: Developers
Classifier: License :: OSI Approved :: Apache Software License
Classifier: Framework :: AsyncIO
Classifier: Typing :: Typed
Classifier: Programming Language :: Python
Classifier: Programming Language :: Python :: 3
Classifier: Programming Language :: Python :: 3.8
Classifier: Programming Language :: Python :: 3.9
Classifier: Programming Language :: Python :: 3.10
Classifier: Programming Language :: Python :: 3.11
Classifier: Programming Language :: Python :: 3.12
Requires-Python: >=3.8
License-File: LICENSE
Requires-Dist: asphalt ~=4.8
Requires-Dist: py4j >=0.10.9
Provides-Extra: doc
Requires-Dist: Sphinx >=7.0 ; extra == 'doc'
Requires-Dist: sphinx-rtd-theme >=1.3.0 ; extra == 'doc'
Requires-Dist: sphinx-autodoc-typehints >=1.22 ; extra == 'doc'
Provides-Extra: test
Requires-Dist: anyio >=4.0 ; extra == 'test'
Requires-Dist: coverage >=7 ; extra == 'test'
Requires-Dist: pytest ; extra == 'test'
